[
null,
{"id":1,"list":[{"code":108,"indent":0,"parameters":["「レースバトル」"]},{"code":356,"indent":0,"parameters":["RaceBattle switch 1"]},{"code":108,"indent":0,"parameters":["|"]},{"code":408,"indent":0,"parameters":["敵の数"]},{"code":356,"indent":0,"parameters":["RaceBattle enemies 1"]},{"code":108,"indent":0,"parameters":["|"]},{"code":408,"indent":0,"parameters":["地面はダート"]},{"code":356,"indent":0,"parameters":["RaceBattle ground 1"]},{"code":108,"indent":0,"parameters":["|"]},{"code":408,"indent":0,"parameters":["埒の種類"]},{"code":356,"indent":0,"parameters":["RaceBattle fence 0"]},{"code":108,"indent":0,"parameters":["|"]},{"code":408,"indent":0,"parameters":["レース名"]},{"code":356,"indent":0,"parameters":["RaceBattle raceTitle 直線レース"]},{"code":108,"indent":0,"parameters":["|"]},{"code":408,"indent":0,"parameters":["障害物なし"]},{"code":356,"indent":0,"parameters":["RaceBattle obstacle easy 0 0"]},{"code":356,"indent":0,"parameters":["RaceBattle obstacle normal 0 0"]},{"code":356,"indent":0,"parameters":["RaceBattle obstacle hard 0 0"]},{"code":108,"indent":0,"parameters":["|"]},{"code":408,"indent":0,"parameters":["ＩＰキャラ装備はなし"]},{"code":108,"indent":0,"parameters":["|"]},{"code":408,"indent":0,"parameters":["ＩＰキャラからの応援はなし"]},{"code":108,"indent":0,"parameters":["|"]},{"code":408,"indent":0,"parameters":["各馬のパラメーター(自馬だけ設定)"]},{"code":356,"indent":0,"parameters":["RaceBattle param 0 1000 50 50 50"]},{"code":108,"indent":0,"parameters":["|"]},{"code":408,"indent":0,"parameters":["各馬の名前"]},{"code":356,"indent":0,"parameters":["RaceBattle charaName 0 馬一郎"]},{"code":356,"indent":0,"parameters":["RaceBattle charaName 1 馬二郎"]},{"code":108,"indent":0,"parameters":["|"]},{"code":408,"indent":0,"parameters":["自馬のスキル"]},{"code":356,"indent":0,"parameters":["RaceBattle skill 1"]},{"code":356,"indent":0,"parameters":["RaceBattle skill 2"]},{"code":356,"indent":0,"parameters":["RaceBattle skill 3"]},{"code":108,"indent":0,"parameters":["|"]},{"code":408,"indent":0,"parameters":["着順を格納する変数番号"]},{"code":356,"indent":0,"parameters":["RaceBattle arrival 1 2"]},{"code":108,"indent":0,"parameters":["|"]},{"code":408,"indent":0,"parameters":["順位順に馬名格納変数番号"]},{"code":356,"indent":0,"parameters":["RaceBattle rankingName 11 12"]},{"code":108,"indent":0,"parameters":["|"]},{"code":408,"indent":0,"parameters":["ヘルプ非表示"]},{"code":108,"indent":0,"parameters":["|"]},{"code":408,"indent":0,"parameters":["ヘルプ内容未設定"]},{"code":108,"indent":0,"parameters":["|"]},{"code":408,"indent":0,"parameters":["コース内容"]},{"code":356,"indent":0,"parameters":["RaceBattle course 1000 front 600 front"]},{"code":108,"indent":0,"parameters":["|"]},{"code":408,"indent":0,"parameters":["レースＢＧＭの設定"]},{"code":356,"indent":0,"parameters":["RaceBattle bgm Battle1 90 100 Theme6 90 100"]},{"code":108,"indent":0,"parameters":["|"]},{"code":408,"indent":0,"parameters":["レーススタート"]},{"code":301,"indent":0,"parameters":[0,1,false,false]},{"code":356,"indent":0,"parameters":["RaceBattle switch 0"]},{"code":0,"indent":0,"parameters":[]}],"name":"２頭直線コース(競り合いなし)","switchId":1,"trigger":0},
{"id":2,"list":[{"code":108,"indent":0,"parameters":["「レースバトル」"]},{"code":356,"indent":0,"parameters":["RaceBattle switch 1"]},{"code":108,"indent":0,"parameters":["|"]},{"code":408,"indent":0,"parameters":["敵の数"]},{"code":356,"indent":0,"parameters":["RaceBattle enemies 1"]},{"code":108,"indent":0,"parameters":["|"]},{"code":408,"indent":0,"parameters":["地面は芝"]},{"code":356,"indent":0,"parameters":["RaceBattle ground 0"]},{"code":108,"indent":0,"parameters":["|"]},{"code":408,"indent":0,"parameters":["埒の種類"]},{"code":356,"indent":0,"parameters":["RaceBattle fence 1"]},{"code":108,"indent":0,"parameters":["|"]},{"code":408,"indent":0,"parameters":["レース名"]},{"code":356,"indent":0,"parameters":["RaceBattle raceTitle 直線レース"]},{"code":108,"indent":0,"parameters":["|"]},{"code":408,"indent":0,"parameters":["障害物なし"]},{"code":356,"indent":0,"parameters":["RaceBattle obstacle easy 0 0"]},{"code":356,"indent":0,"parameters":["RaceBattle obstacle normal 0 0"]},{"code":356,"indent":0,"parameters":["RaceBattle obstacle hard 0 0"]},{"code":108,"indent":0,"parameters":["|"]},{"code":408,"indent":0,"parameters":["ＩＰキャラ装備はなし"]},{"code":108,"indent":0,"parameters":["|"]},{"code":408,"indent":0,"parameters":["ＩＰキャラからの応援はなし"]},{"code":108,"indent":0,"parameters":["|"]},{"code":408,"indent":0,"parameters":["各馬のパラメーター(自馬だけ設定)"]},{"code":356,"indent":0,"parameters":["RaceBattle param 0 1000 50 50 50"]},{"code":108,"indent":0,"parameters":["|"]},{"code":408,"indent":0,"parameters":["各馬の名前"]},{"code":356,"indent":0,"parameters":["RaceBattle charaName 0 馬一郎"]},{"code":356,"indent":0,"parameters":["RaceBattle charaName 1 馬二郎"]},{"code":108,"indent":0,"parameters":["|"]},{"code":408,"indent":0,"parameters":["自馬のスキル"]},{"code":356,"indent":0,"parameters":["RaceBattle skill 1"]},{"code":356,"indent":0,"parameters":["RaceBattle skill 2"]},{"code":356,"indent":0,"parameters":["RaceBattle skill 3"]},{"code":108,"indent":0,"parameters":["|"]},{"code":408,"indent":0,"parameters":["着順を格納する変数番号"]},{"code":356,"indent":0,"parameters":["RaceBattle arrival 1 2"]},{"code":108,"indent":0,"parameters":["|"]},{"code":408,"indent":0,"parameters":["順位順に馬名格納変数番号"]},{"code":356,"indent":0,"parameters":["RaceBattle rankingName 11 12"]},{"code":108,"indent":0,"parameters":["|"]},{"code":408,"indent":0,"parameters":["ヘルプ非表示"]},{"code":108,"indent":0,"parameters":["|"]},{"code":408,"indent":0,"parameters":["ヘルプ内容未設定"]},{"code":108,"indent":0,"parameters":["|"]},{"code":408,"indent":0,"parameters":["コース内容"]},{"code":356,"indent":0,"parameters":["RaceBattle course 1000 front 800 compete 600 front"]},{"code":108,"indent":0,"parameters":["|"]},{"code":408,"indent":0,"parameters":["レースＢＧＭの設定"]},{"code":356,"indent":0,"parameters":["RaceBattle bgm Battle1 90 100 Theme6 90 100"]},{"code":108,"indent":0,"parameters":["|"]},{"code":408,"indent":0,"parameters":["レーススタート"]},{"code":301,"indent":0,"parameters":[0,1,false,false]},{"code":356,"indent":0,"parameters":["RaceBattle switch 0"]},{"code":0,"indent":0,"parameters":[]}],"name":"２頭直線コース(競り合いあり)","switchId":1,"trigger":0},
{"id":3,"list":[{"code":108,"indent":0,"parameters":["「レースバトル」"]},{"code":356,"indent":0,"parameters":["RaceBattle switch 1"]},{"code":108,"indent":0,"parameters":["|"]},{"code":408,"indent":0,"parameters":["敵の数"]},{"code":356,"indent":0,"parameters":["RaceBattle enemies 4"]},{"code":108,"indent":0,"parameters":["|"]},{"code":408,"indent":0,"parameters":["地面は芝"]},{"code":356,"indent":0,"parameters":["RaceBattle ground 0"]},{"code":108,"indent":0,"parameters":["|"]},{"code":408,"indent":0,"parameters":["埒の種類"]},{"code":356,"indent":0,"parameters":["RaceBattle fence 2"]},{"code":108,"indent":0,"parameters":["|"]},{"code":408,"indent":0,"parameters":["レース名"]},{"code":356,"indent":0,"parameters":["RaceBattle raceTitle 一般レース"]},{"code":108,"indent":0,"parameters":["|"]},{"code":408,"indent":0,"parameters":["障害物なし"]},{"code":356,"indent":0,"parameters":["RaceBattle obstacle easy 0 0"]},{"code":356,"indent":0,"parameters":["RaceBattle obstacle normal 0 0"]},{"code":356,"indent":0,"parameters":["RaceBattle obstacle hard 0 0"]},{"code":108,"indent":0,"parameters":["|"]},{"code":408,"indent":0,"parameters":["ＩＰキャラ装備はなし"]},{"code":108,"indent":0,"parameters":["|"]},{"code":408,"indent":0,"parameters":["ＩＰキャラからの応援はなし"]},{"code":108,"indent":0,"parameters":["|"]},{"code":408,"indent":0,"parameters":["各馬のパラメーター(自馬だけ設定)"]},{"code":356,"indent":0,"parameters":["RaceBattle param 0 1000 50 50 50"]},{"code":108,"indent":0,"parameters":["|"]},{"code":408,"indent":0,"parameters":["各馬の名前"]},{"code":356,"indent":0,"parameters":["RaceBattle charaName 0 馬一郎"]},{"code":356,"indent":0,"parameters":["RaceBattle charaName 1 馬二郎"]},{"code":356,"indent":0,"parameters":["RaceBattle charaName 2 馬三郎"]},{"code":356,"indent":0,"parameters":["RaceBattle charaName 3 馬四郎"]},{"code":356,"indent":0,"parameters":["RaceBattle charaName 4 馬五郎"]},{"code":108,"indent":0,"parameters":["|"]},{"code":408,"indent":0,"parameters":["自馬のスキル"]},{"code":356,"indent":0,"parameters":["RaceBattle skill 1"]},{"code":356,"indent":0,"parameters":["RaceBattle skill 2"]},{"code":356,"indent":0,"parameters":["RaceBattle skill 3"]},{"code":108,"indent":0,"parameters":["|"]},{"code":408,"indent":0,"parameters":["着順を格納する変数番号"]},{"code":356,"indent":0,"parameters":["RaceBattle arrival 1 2 3 4 5"]},{"code":108,"indent":0,"parameters":["|"]},{"code":408,"indent":0,"parameters":["順位順に馬名格納変数番号"]},{"code":356,"indent":0,"parameters":["RaceBattle rankingName 11 12 13 14 15"]},{"code":108,"indent":0,"parameters":["|"]},{"code":408,"indent":0,"parameters":["ヘルプ非表示"]},{"code":108,"indent":0,"parameters":["|"]},{"code":408,"indent":0,"parameters":["ヘルプ内容未設定"]},{"code":108,"indent":0,"parameters":["|"]},{"code":408,"indent":0,"parameters":["コース内容"]},{"code":356,"indent":0,"parameters":["RaceBattle course 2400 front 2200 compete 2000 front 1800 compete 1600 upCorner 1400 compete 1200 overthere 1000 compete 800 downCorner 600 front"]},{"code":108,"indent":0,"parameters":["|"]},{"code":408,"indent":0,"parameters":["レースＢＧＭの設定"]},{"code":356,"indent":0,"parameters":["RaceBattle bgm Battle1 90 100 Theme6 90 100"]},{"code":108,"indent":0,"parameters":["|"]},{"code":408,"indent":0,"parameters":["レーススタート"]},{"code":301,"indent":0,"parameters":[0,1,false,false]},{"code":356,"indent":0,"parameters":["RaceBattle switch 0"]},{"code":0,"indent":0,"parameters":[]}],"name":"５頭一般コース(障害物なし)","switchId":1,"trigger":0},
{"id":4,"list":[{"code":108,"indent":0,"parameters":["「レースバトル」"]},{"code":356,"indent":0,"parameters":["RaceBattle switch 1"]},{"code":108,"indent":0,"parameters":["|"]},{"code":408,"indent":0,"parameters":["敵の数"]},{"code":356,"indent":0,"parameters":["RaceBattle enemies 7"]},{"code":108,"indent":0,"parameters":["|"]},{"code":408,"indent":0,"parameters":["地面は芝"]},{"code":356,"indent":0,"parameters":["RaceBattle ground 0"]},{"code":108,"indent":0,"parameters":["|"]},{"code":408,"indent":0,"parameters":["埒の種類"]},{"code":356,"indent":0,"parameters":["RaceBattle fence 3"]},{"code":108,"indent":0,"parameters":["|"]},{"code":408,"indent":0,"parameters":["レース名"]},{"code":356,"indent":0,"parameters":["RaceBattle raceTitle 一般レース"]},{"code":108,"indent":0,"parameters":["|"]},{"code":408,"indent":0,"parameters":["障害物あり"]},{"code":356,"indent":0,"parameters":["RaceBattle obstacle easy 5 75"]},{"code":356,"indent":0,"parameters":["RaceBattle obstacle normal 10 70"]},{"code":356,"indent":0,"parameters":["RaceBattle obstacle hard 15 65"]},{"code":108,"indent":0,"parameters":["|"]},{"code":408,"indent":0,"parameters":["ＩＰキャラ装備はなし"]},{"code":108,"indent":0,"parameters":["|"]},{"code":408,"indent":0,"parameters":["ＩＰキャラからの応援はなし"]},{"code":108,"indent":0,"parameters":["|"]},{"code":408,"indent":0,"parameters":["各馬のパラメーター(自馬だけ設定)"]},{"code":356,"indent":0,"parameters":["RaceBattle param 0 1000 50 50 50"]},{"code":108,"indent":0,"parameters":["|"]},{"code":408,"indent":0,"parameters":["各馬の名前"]},{"code":356,"indent":0,"parameters":["RaceBattle charaName 0 馬一郎"]},{"code":356,"indent":0,"parameters":["RaceBattle charaName 1 馬二郎"]},{"code":356,"indent":0,"parameters":["RaceBattle charaName 2 馬三郎"]},{"code":356,"indent":0,"parameters":["RaceBattle charaName 3 馬四郎"]},{"code":356,"indent":0,"parameters":["RaceBattle charaName 4 馬五郎"]},{"code":356,"indent":0,"parameters":["RaceBattle charaName 5 馬六郎"]},{"code":356,"indent":0,"parameters":["RaceBattle charaName 6 馬七郎"]},{"code":356,"indent":0,"parameters":["RaceBattle charaName 7 馬八郎"]},{"code":108,"indent":0,"parameters":["|"]},{"code":408,"indent":0,"parameters":["自馬のスキル"]},{"code":356,"indent":0,"parameters":["RaceBattle skill 1"]},{"code":356,"indent":0,"parameters":["RaceBattle skill 2"]},{"code":356,"indent":0,"parameters":["RaceBattle skill 3"]},{"code":108,"indent":0,"parameters":["|"]},{"code":408,"indent":0,"parameters":["着順を格納する変数番号"]},{"code":356,"indent":0,"parameters":["RaceBattle arrival 1 2 3 4 5 6 7 8"]},{"code":108,"indent":0,"parameters":["|"]},{"code":408,"indent":0,"parameters":["順位順に馬名格納変数番号"]},{"code":356,"indent":0,"parameters":["RaceBattle rankingName 11 12 13 14 15 16 17 18"]},{"code":108,"indent":0,"parameters":["|"]},{"code":408,"indent":0,"parameters":["ヘルプ非表示"]},{"code":108,"indent":0,"parameters":["|"]},{"code":408,"indent":0,"parameters":["ヘルプ内容未設定"]},{"code":108,"indent":0,"parameters":["|"]},{"code":408,"indent":0,"parameters":["コース内容"]},{"code":356,"indent":0,"parameters":["RaceBattle course 2400 front 2200 compete 2000 front 1800 compete 1600 upCorner 1400 compete 1200 overthere 1000 compete 800 downCorner 600 front"]},{"code":108,"indent":0,"parameters":["|"]},{"code":408,"indent":0,"parameters":["レースＢＧＭの設定"]},{"code":356,"indent":0,"parameters":["RaceBattle bgm Battle1 90 100 Theme6 90 100"]},{"code":108,"indent":0,"parameters":["|"]},{"code":408,"indent":0,"parameters":["レーススタート"]},{"code":301,"indent":0,"parameters":[0,1,false,false]},{"code":356,"indent":0,"parameters":["RaceBattle switch 0"]},{"code":0,"indent":0,"parameters":[]}],"name":"８頭一般コース(障害物あり)","switchId":1,"trigger":0},
{"id":5,"list":[{"code":108,"indent":0,"parameters":["「レースバトル」"]},{"code":356,"indent":0,"parameters":["RaceBattle switch 1"]},{"code":108,"indent":0,"parameters":["|"]},{"code":408,"indent":0,"parameters":["敵の数"]},{"code":356,"indent":0,"parameters":["RaceBattle enemies 7"]},{"code":108,"indent":0,"parameters":["|"]},{"code":408,"indent":0,"parameters":["地面はダート"]},{"code":356,"indent":0,"parameters":["RaceBattle ground 1"]},{"code":108,"indent":0,"parameters":["|"]},{"code":408,"indent":0,"parameters":["埒の種類"]},{"code":356,"indent":0,"parameters":["RaceBattle fence 4"]},{"code":108,"indent":0,"parameters":["|"]},{"code":408,"indent":0,"parameters":["レース名"]},{"code":356,"indent":0,"parameters":["RaceBattle raceTitle チュートリアルレース"]},{"code":108,"indent":0,"parameters":["|"]},{"code":408,"indent":0,"parameters":["障害物あり"]},{"code":356,"indent":0,"parameters":["RaceBattle obstacle easy 5 75"]},{"code":356,"indent":0,"parameters":["RaceBattle obstacle normal 10 70"]},{"code":356,"indent":0,"parameters":["RaceBattle obstacle hard 15 65"]},{"code":108,"indent":0,"parameters":["|"]},{"code":408,"indent":0,"parameters":["全ＩＰキャラ装備"]},{"code":356,"indent":0,"parameters":["RaceBattle equip 1 2 3"]},{"code":108,"indent":0,"parameters":["|"]},{"code":408,"indent":0,"parameters":["全ＩＰキャラから１回応援"]},{"code":356,"indent":0,"parameters":["RaceBattle cheer 1 1 1"]},{"code":108,"indent":0,"parameters":["|"]},{"code":408,"indent":0,"parameters":["各馬のパラメーター(自馬だけ設定)"]},{"code":356,"indent":0,"parameters":["RaceBattle param 0 1000 50 50 50"]},{"code":108,"indent":0,"parameters":["|"]},{"code":408,"indent":0,"parameters":["各馬の名前"]},{"code":356,"indent":0,"parameters":["RaceBattle charaName 0 馬一郎"]},{"code":356,"indent":0,"parameters":["RaceBattle charaName 1 馬二郎"]},{"code":356,"indent":0,"parameters":["RaceBattle charaName 2 馬三郎"]},{"code":356,"indent":0,"parameters":["RaceBattle charaName 3 馬四郎"]},{"code":356,"indent":0,"parameters":["RaceBattle charaName 4 馬五郎"]},{"code":356,"indent":0,"parameters":["RaceBattle charaName 5 馬六郎"]},{"code":356,"indent":0,"parameters":["RaceBattle charaName 6 馬七郎"]},{"code":356,"indent":0,"parameters":["RaceBattle charaName 7 馬八郎"]},{"code":108,"indent":0,"parameters":["|"]},{"code":408,"indent":0,"parameters":["自馬のスキル"]},{"code":356,"indent":0,"parameters":["RaceBattle skill 1"]},{"code":356,"indent":0,"parameters":["RaceBattle skill 2"]},{"code":356,"indent":0,"parameters":["RaceBattle skill 3"]},{"code":108,"indent":0,"parameters":["|"]},{"code":408,"indent":0,"parameters":["着順を格納する変数番号"]},{"code":356,"indent":0,"parameters":["RaceBattle arrival 1 2 3 4 5 6 7 8"]},{"code":108,"indent":0,"parameters":["|"]},{"code":408,"indent":0,"parameters":["順位順に馬名格納変数番号"]},{"code":356,"indent":0,"parameters":["RaceBattle rankingName 11 12 13 14 15 16 17 18"]},{"code":108,"indent":0,"parameters":["|"]},{"code":408,"indent":0,"parameters":["ヘルプ表示"]},{"code":356,"indent":0,"parameters":["RaceBattle help 1"]},{"code":108,"indent":0,"parameters":["|"]},{"code":408,"indent":0,"parameters":["ヘルプ文言設定"]},{"code":356,"indent":0,"parameters":["RaceBattle helpText compete \\n#98ff90■About the competitive phase: It is a phase that competes with each other in the \\n\\n restricted turn and competes for \\n [remaining stamina amount] by racehorses shaving each other's stamina. Four horses around \\n, including their own horses, are selected, and after the restriction turn is the horse with the most residual stamina, the horse with the most remaining stamina is the first place. \\n\\n#ffcc20 `Competition` command\\n Let's select the horse you want to shave your stamina. When the stamina is zero, the horse becomes a retirement. \\n\\n#ffcc20 `Distract` command \\n Instead of not competing against the opponent's horse, \\n's own horse can halve the stamina that is shaved by the race."]},{"code":356,"indent":0,"parameters":["RaceBattle helpText move #98ff90■About the movement instruction phase: \\n\\n A phase that selects the movement location and skill. The course information to run next is also displayed, so let's refer to the \\n instruction. \\n\\n#ffcc20 `Move` command\\\n Press the arrow in the direction you want to move to determine. The probability of success of the \\n movement instruction is determined based on the result of the competition. \\n `▲` ... intrudes into the in-course. \\n `◀` ... Increase the speed and move forward. \\n `▶` ... retreat and perform a stamina recovery of 5-10%. \\n `▼` ... intrudes into the outcourse. \\n\\n#ffcc20 `Skills` command\\\n You can choose only one skill to use. The number of times the use and the timing of effect are different for each \\n skill."]},{"code":356,"indent":0,"parameters":["RaceBattle helpText racing \\n\\n\\n#98ff90■About the running phase: \\n\\n It is an auto progressive phase that watches the running of the horse. The move to the destination specified in the \\n movement instruction phase is reflected. The horse's stamina decreases automatically while running \\n\\n, and when the \\n stamina is zero, it becomes retirement. When the horse's `heightness` is high, the driving speed increases, and when the `heightness` of the horse is high, the probability that obstacles can be avoided increases."]},{"code":356,"indent":0,"parameters":["RaceBattle helpText last_spurt \\n\\n\\n#98ff90■About the last spurt phase: \\n\\n In the last straight line, switch from \\n running phase to last sper phase. You can push the whip button up to \\n\\n three times to boost. However, it consumes twenty percent of the maximum stamina of the \\n horse for one use of the whip. Let's pull away the opponent with the \\n whip button while paying attention to the remaining stamina amount."]},{"code":108,"indent":0,"parameters":["|"]},{"code":408,"indent":0,"parameters":["コース内容"]},{"code":356,"indent":0,"parameters":["RaceBattle course 2400 front 2200 compete 1800 upCorner 1500 overthere 900 downCorner 600 front"]},{"code":108,"indent":0,"parameters":["|"]},{"code":408,"indent":0,"parameters":["レースＢＧＭの設定"]},{"code":356,"indent":0,"parameters":["RaceBattle bgm Battle1 90 100 Theme6 90 100"]},{"code":108,"indent":0,"parameters":["|"]},{"code":408,"indent":0,"parameters":["レーススタート"]},{"code":301,"indent":0,"parameters":[0,1,false,false]},{"code":356,"indent":0,"parameters":["RaceBattle switch 0"]},{"code":0,"indent":0,"parameters":[]}],"name":"チュートリアルコース(ヘルプあり)","switchId":1,"trigger":0}
]